g_mmpbsa/__init__.py
g_mmpbsa/_version.py
g_mmpbsa/average.py
g_mmpbsa/correlation.py
g_mmpbsa/decompose.py
g_mmpbsa/g_mmpbsa.cpython-311-x86_64-linux-gnu.so
g_mmpbsa/main.py
g_mmpbsa.libs/libamd-a26d1aab.so.2.4.1
g_mmpbsa.libs/libapbs_fem-962c21e6.so
g_mmpbsa.libs/libapbs_generic-a0e9439f.so
g_mmpbsa.libs/libapbs_mg-cb05b59c.so
g_mmpbsa.libs/libapbs_pmgc-bd47fa23.so
g_mmpbsa.libs/libapbs_routines-40cd6dde.so
g_mmpbsa.libs/libarpack-042921fd.so.2.1.0
g_mmpbsa.libs/libcamd-28bb7d13.so.2.4.1
g_mmpbsa.libs/libccolamd-b4f1d742.so.2.9.1
g_mmpbsa.libs/libcgcode-84cbdb00.so
g_mmpbsa.libs/libcholmod-8f6cf142.so.3.0.6
g_mmpbsa.libs/libcolamd-dc193ab4.so.2.9.1
g_mmpbsa.libs/libgfortran-83c28eba.so.5.0.0
g_mmpbsa.libs/libgomp-e985bcbb.so.1.0.0
g_mmpbsa.libs/libgromacs-ba10bb3d.so.10.0.0
g_mmpbsa.libs/libiapbs-b4340b5f.so
g_mmpbsa.libs/libmaloc-84bbb1c8.so
g_mmpbsa.libs/libmc-ef6d7dcb.so
g_mmpbsa.libs/libmuparser-b3aa0e13.so.2.3.4
g_mmpbsa.libs/libopenblas-r0-11edc3fa.3.15.so
g_mmpbsa.libs/libopenblasp-r0-59ffcd50.3.15.so
g_mmpbsa.libs/libpunc-b4145af2.so
g_mmpbsa.libs/libquadmath-2284e583.so.0.0.0
g_mmpbsa.libs/libsatlas-6c1f674f.so.3.10
g_mmpbsa.libs/libspqr-896e91c7.so.2.0.1
g_mmpbsa.libs/libsuitesparseconfig-e4e8c4aa.so.4.4.4
g_mmpbsa.libs/libsuperlu-0682d986.so.5.3.0
g_mmpbsa.libs/libtbb-f09e8534.so.2
g_mmpbsa.libs/libumfpack-2e055419.so.5.7.1
g_mmpbsa.libs/libvf2c-221cf6eb.so
g_mmpbsa-3.0.13.dist-info/METADATA
g_mmpbsa-3.0.13.dist-info/WHEEL
g_mmpbsa-3.0.13.dist-info/entry_points.txt
g_mmpbsa-3.0.13.dist-info/top_level.txt
g_mmpbsa-3.0.13.dist-info/RECORD
g_mmpbsa-3.0.13.dist-info/licenses/COPYING
g_mmpbsa-3.0.13.dist-info/sboms/auditwheel.cdx.json
