Metadata-Version: 2.4
Name: g_mmpbsa
Version: 3.0.13
Summary: MM/PBSA calculations for GROMACS.
Author: Rashmi Kumari
Author-email: Rajendra Kumar <rjdkmr@gmail.com>
License: GNU General Public License v3 (GPLv3)
Project-URL: homepage, https://g-mmpbsa.readthedocs.io/
Project-URL: repository, https://github.com/rjdkmr/g_mmpbsa/
Keywords: Molecular Modeling,Molecular Dynamics Simulations,Computational Chemistry,Computational Biophysics,MM/PBSA
Classifier: Environment :: Console
Classifier: Intended Audience :: Developers
Classifier: Intended Audience :: End Users/Desktop
Classifier: Intended Audience :: Science/Research
Classifier: License :: OSI Approved :: GNU General Public License v3 (GPLv3)
Classifier: Natural Language :: English
Classifier: Operating System :: MacOS
Classifier: Operating System :: POSIX :: Linux
Classifier: Topic :: Scientific/Engineering :: Chemistry
Classifier: Topic :: Scientific/Engineering :: Bio-Informatics
License-File: COPYING
Requires-Dist: numpy>=1.6
Requires-Dist: scipy>=0.9
Requires-Dist: matplotlib>=1.1.0
Dynamic: license-file
